nitrate/__init__.py
nitrate/cassettes.py
nitrate/flickr_login.py
nitrate/json.py
nitrate/mock_keyring.py
nitrate/py.typed
nitrate/types.py
nitrate/xml.py
silver_nitrate-1.8.1.dist-info/licenses/LICENSE-APACHE
silver_nitrate-1.8.1.dist-info/licenses/LICENSE-MIT
silver_nitrate-1.8.1.dist-info/METADATA
silver_nitrate-1.8.1.dist-info/WHEEL
silver_nitrate-1.8.1.dist-info/top_level.txt
silver_nitrate-1.8.1.dist-info/RECORD
