Metadata-Version: 2.4
Name: silver-nitrate
Version: 1.8.1
Summary: Python utilities used by the Flickr Foundation
Author-email: Flickr Foundation <hello@flickr.org>
Maintainer-email: Alex Chan <alex@flickr.org>
License-Expression: MIT AND (Apache-2.0)
Project-URL: Homepage, https://github.com/Flickr-Foundation/silver-nitrate
Project-URL: Changelog, https://github.com/Flickr-Foundation/silver-nitrate/blob/main/CHANGELOG.md
Keywords: flickr
Classifier: Development Status :: 5 - Production/Stable
Classifier: Programming Language :: Python :: 3.12
Requires-Python: >=3.12
License-File: LICENSE-APACHE
License-File: LICENSE-MIT
Provides-Extra: cassettes
Requires-Dist: pytest; extra == "cassettes"
Requires-Dist: pytest-vcr; extra == "cassettes"
Provides-Extra: json
Provides-Extra: login
Requires-Dist: authlib; extra == "login"
Requires-Dist: httpx; extra == "login"
Requires-Dist: silver-nitrate[types]; extra == "login"
Provides-Extra: mock-keyring
Requires-Dist: keyring; extra == "mock-keyring"
Requires-Dist: pytest; extra == "mock-keyring"
Provides-Extra: types
Requires-Dist: pydantic; extra == "types"
Provides-Extra: xml
Dynamic: license-file
